MANIFEST.in
README.rst
setup.py
docs/HISTORY.txt
docs/LICENSE.GPL
docs/LICENSE.txt
ftw/__init__.py
ftw.usermanagement.egg-info/PKG-INFO
ftw.usermanagement.egg-info/SOURCES.txt
ftw.usermanagement.egg-info/dependency_links.txt
ftw.usermanagement.egg-info/entry_points.txt
ftw.usermanagement.egg-info/namespace_packages.txt
ftw.usermanagement.egg-info/not-zip-safe
ftw.usermanagement.egg-info/requires.txt
ftw.usermanagement.egg-info/top_level.txt
ftw/usermanagement/__init__.py
ftw/usermanagement/configure.zcml
ftw/usermanagement/interfaces.py
ftw/usermanagement/lawgiver.zcml
ftw/usermanagement/source.py
ftw/usermanagement/testing.py
ftw/usermanagement/browser/__init__.py
ftw/usermanagement/browser/base_listing.py
ftw/usermanagement/browser/configure.zcml
ftw/usermanagement/browser/tabbed_management.py
ftw/usermanagement/browser/group/__init__.py
ftw/usermanagement/browser/group/configure.zcml
ftw/usermanagement/browser/group/error_roles_required.pt
ftw/usermanagement/browser/group/group_add.py
ftw/usermanagement/browser/group/group_delete.pt
ftw/usermanagement/browser/group/group_delete.py
ftw/usermanagement/browser/group/group_membership.pt
ftw/usermanagement/browser/group/group_membership.py
ftw/usermanagement/browser/group/groups.pt
ftw/usermanagement/browser/group/groups.py
ftw/usermanagement/browser/js/user_group.js
ftw/usermanagement/browser/mail_templates/__init__.py
ftw/usermanagement/browser/mail_templates/notify_user_html.pt
ftw/usermanagement/browser/mail_templates/notify_user_html.py
ftw/usermanagement/browser/user/__init__.py
ftw/usermanagement/browser/user/configure.zcml
ftw/usermanagement/browser/user/user_delete.pt
ftw/usermanagement/browser/user/user_delete.py
ftw/usermanagement/browser/user/user_export.py
ftw/usermanagement/browser/user/user_membership.pt
ftw/usermanagement/browser/user/user_membership.py
ftw/usermanagement/browser/user/user_notify.py
ftw/usermanagement/browser/user/user_register.py
ftw/usermanagement/browser/user/users.pt
ftw/usermanagement/browser/user/users.py
ftw/usermanagement/locales/ftw.tabbedview.pot
ftw/usermanagement/locales/ftw.usermanagement-manual.pot
ftw/usermanagement/locales/ftw.usermanagement.pot
ftw/usermanagement/locales/plone.pot
ftw/usermanagement/locales/de/LC_MESSAGES/ftw.tabbedview.po
ftw/usermanagement/locales/de/LC_MESSAGES/ftw.usermanagement.po
