Metadata-Version: 1.1
Name: ftw.usermanagement
Version: 1.10.0
Summary: An advanced view for managing users in plone.
Home-page: https://github.com/4teamwork/ftw.usermanagement
Author: Mathias Leimgruber
Author-email: mailto:info@4teamwork.ch
License: GPL2
Keywords: ftw usermanagement user management view plone
Platform: UNKNOWN
Classifier: Framework :: Plone
Classifier: Framework :: Plone :: 4.2
Classifier: Framework :: Plone :: 4.3
Classifier: Programming Language :: Python
Classifier: Topic :: Software Development :: Libraries :: Python Modules
